Metadata-Version: 1.1
Name: pypopt
Version: 0.6.0
Summary: Bindings to Ipopt C++ library.
Home-page: UNKNOWN
Author: Francesco Ceccon
Author-email: francesco@ceccon.me
License: Apache 2.0
Platform: UNKNOWN
Classifier: Development Status :: 4 - Beta
Classifier: Intended Audience :: Science/Research
Classifier: Programming Language :: Python :: 3.5
Classifier: Programming Language :: Python :: 3.6
Classifier: Topic :: Scientific/Engineering :: Mathematics
